README.md
setup.cfg
setup.py
kerasparalleltext/__init__.py
kerasparalleltext/preprocess.py
kerasparalleltext.egg-info/PKG-INFO
kerasparalleltext.egg-info/SOURCES.txt
kerasparalleltext.egg-info/dependency_links.txt
kerasparalleltext.egg-info/requires.txt
kerasparalleltext.egg-info/top_level.txt