Metadata-Version: 1.1
Name: kerasparalleltext
Version: 0.20
Summary: Pre-processing text in parallel for Keras in python.
Home-page: https://github.com/hamelsmu/KerasParallelText
Author: Hamel Husain
Author-email: hamel.husain@gmail.com
License: MIT
Download-URL: https://github.com/hamelsmu/KerasParallelText/archive/0.20.tar.gz
Platform: UNKNOWN
Classifier: Development Status :: 1 - Planning
Classifier: Programming Language :: Python :: 3.6
Classifier: Topic :: Software Development :: Libraries
Classifier: Topic :: Software Development :: Libraries :: Python Modules
